selOpe/__init__.py
selOpe/client/__init__.py
selOpe/client/client_common.py
selOpe/client/client_operator.py
selOpe/db/__init__.py
selOpe/db/connect_db.py
selOpe/web/__init__.py
selOpe/web/driver_config.py
selOpe/web/web_operator.py
selOp-2.5.dist-info/METADATA
selOp-2.5.dist-info/WHEEL
selOp-2.5.dist-info/top_level.txt
selOp-2.5.dist-info/RECORD
