Metadata-Version: 2.1
Name: selOp
Version: 2.5
Summary: A tool for Selenium element operations.
Home-page: UNKNOWN
Author: Myf
Author-email: 
License: UNKNOWN
Platform: UNKNOWN
Classifier: Programming Language :: Python :: 3
Classifier: License :: OSI Approved :: MIT License
Classifier: Operating System :: OS Independent
Requires-Python: >=3.8
Requires-Dist: selenium
Requires-Dist: sqlite3
